{
  "status":202,
  "url":"https://api.github.com/repos/Kristie-Tom-Test/HelloWorld/forks",
  "headers":{
     "access-control-allow-origin":"*",
     "access-control-expose-headers":"ETag, Link, Location, Retry-After, X-GitHub-OTP, X-RateLimit-Limit, X-RateLimit-Remaining, X-RateLimit-Reset, X-OAuth-Scopes, X-Accepted-OAuth-Scopes, X-Poll-Interval, X-GitHub-Media-Type, Deprecation, Sunset",
     "connection":"close",
     "content-length":"15507",
     "content-security-policy":"default-src 'none'",
     "content-type":"application/json; charset=utf-8",
     "date":"Mon, 15 Jun 2020 23:53:49 GMT",
     "referrer-policy":"origin-when-cross-origin, strict-origin-when-cross-origin",
     "server":"GitHub.com",
     "status":"202 Accepted",
     "strict-transport-security":"max-age=31536000; includeSubdomains; preload",
     "vary":"Accept-Encoding, Accept, X-Requested-With",
     "x-accepted-oauth-scopes":"",
     "x-content-type-options":"nosniff",
     "x-frame-options":"deny",
     "x-github-media-type":"github.v3; format=json",
     "x-github-request-id":"98D2:393F:2E36877:4F7FBEB:5EE80A0D",
     "x-oauth-scopes":"admin:org, repo",
     "x-ratelimit-limit":"5000",
     "x-ratelimit-remaining":"4995",
     "x-ratelimit-reset":"1592267977",
     "x-xss-protection":"1; mode=block"
  },
  "data":{
     "id":1,
     "node_id":"MDEwOlJlcG9zaXRvcnkyNzI1Njc3NzU=",
     "name":"HelloWorld",
     "full_name":"TomKristie/HelloWorld",
     "private":false,
     "owner":{
        "login":"TomKristie",
        "id":2,
        "node_id":"MDQ6VXNlcjY1Njg1NDE3",
        "avatar_url":"https://avatars3.githubusercontent.com/u/65685417?v=4",
        "gravatar_id":"",
        "url":"https://api.github.com/users/TomKristie",
        "html_url":"https://github.com/TomKristie",
        "followers_url":"https://api.github.com/users/TomKristie/followers",
        "following_url":"https://api.github.com/users/TomKristie/following{/other_user}",
        "gists_url":"https://api.github.com/users/TomKristie/gists{/gist_id}",
        "starred_url":"https://api.github.com/users/TomKristie/starred{/owner}{/repo}",
        "subscriptions_url":"https://api.github.com/users/TomKristie/subscriptions",
        "organizations_url":"https://api.github.com/users/TomKristie/orgs",
        "repos_url":"https://api.github.com/users/TomKristie/repos",
        "events_url":"https://api.github.com/users/TomKristie/events{/privacy}",
        "received_events_url":"https://api.github.com/users/TomKristie/received_events",
        "type":"User",
        "site_admin":false
     },
     "html_url":"https://github.com/TomKristie/HelloWorld",
     "description":null,
     "fork":true,
     "url":"https://api.github.com/repos/TomKristie/HelloWorld",
     "forks_url":"https://api.github.com/repos/TomKristie/HelloWorld/forks",
     "keys_url":"https://api.github.com/repos/TomKristie/HelloWorld/keys{/key_id}",
     "collaborators_url":"https://api.github.com/repos/TomKristie/HelloWorld/collaborators{/collaborator}",
     "teams_url":"https://api.github.com/repos/TomKristie/HelloWorld/teams",
     "hooks_url":"https://api.github.com/repos/TomKristie/HelloWorld/hooks",
     "issue_events_url":"https://api.github.com/repos/TomKristie/HelloWorld/issues/events{/number}",
     "events_url":"https://api.github.com/repos/TomKristie/HelloWorld/events",
     "assignees_url":"https://api.github.com/repos/TomKristie/HelloWorld/assignees{/user}",
     "branches_url":"https://api.github.com/repos/TomKristie/HelloWorld/branches{/branch}",
     "tags_url":"https://api.github.com/repos/TomKristie/HelloWorld/tags",
     "blobs_url":"https://api.github.com/repos/TomKristie/HelloWorld/git/blobs{/sha}",
     "git_tags_url":"https://api.github.com/repos/TomKristie/HelloWorld/git/tags{/sha}",
     "git_refs_url":"https://api.github.com/repos/TomKristie/HelloWorld/git/refs{/sha}",
     "trees_url":"https://api.github.com/repos/TomKristie/HelloWorld/git/trees{/sha}",
     "statuses_url":"https://api.github.com/repos/TomKristie/HelloWorld/statuses/{sha}",
     "languages_url":"https://api.github.com/repos/TomKristie/HelloWorld/languages",
     "stargazers_url":"https://api.github.com/repos/TomKristie/HelloWorld/stargazers",
     "contributors_url":"https://api.github.com/repos/TomKristie/HelloWorld/contributors",
     "subscribers_url":"https://api.github.com/repos/TomKristie/HelloWorld/subscribers",
     "subscription_url":"https://api.github.com/repos/TomKristie/HelloWorld/subscription",
     "commits_url":"https://api.github.com/repos/TomKristie/HelloWorld/commits{/sha}",
     "git_commits_url":"https://api.github.com/repos/TomKristie/HelloWorld/git/commits{/sha}",
     "comments_url":"https://api.github.com/repos/TomKristie/HelloWorld/comments{/number}",
     "issue_comment_url":"https://api.github.com/repos/TomKristie/HelloWorld/issues/comments{/number}",
     "contents_url":"https://api.github.com/repos/TomKristie/HelloWorld/contents/{+path}",
     "compare_url":"https://api.github.com/repos/TomKristie/HelloWorld/compare/{base}...{head}",
     "merges_url":"https://api.github.com/repos/TomKristie/HelloWorld/merges",
     "archive_url":"https://api.github.com/repos/TomKristie/HelloWorld/{archive_format}{/ref}",
     "downloads_url":"https://api.github.com/repos/TomKristie/HelloWorld/downloads",
     "issues_url":"https://api.github.com/repos/TomKristie/HelloWorld/issues{/number}",
     "pulls_url":"https://api.github.com/repos/TomKristie/HelloWorld/pulls{/number}",
     "milestones_url":"https://api.github.com/repos/TomKristie/HelloWorld/milestones{/number}",
     "notifications_url":"https://api.github.com/repos/TomKristie/HelloWorld/notifications{?since,all,participating}",
     "labels_url":"https://api.github.com/repos/TomKristie/HelloWorld/labels{/name}",
     "releases_url":"https://api.github.com/repos/TomKristie/HelloWorld/releases{/id}",
     "deployments_url":"https://api.github.com/repos/TomKristie/HelloWorld/deployments",
     "created_at":"2020-06-15T23:53:49Z",
     "updated_at":"2020-06-10T18:27:31Z",
     "pushed_at":"2020-06-10T18:27:29Z",
     "git_url":"git://github.com/TomKristie/HelloWorld.git",
     "ssh_url":"git@github.com:TomKristie/HelloWorld.git",
     "clone_url":"https://github.com/TomKristie/HelloWorld.git",
     "svn_url":"https://github.com/TomKristie/HelloWorld",
     "homepage":null,
     "size":0,
     "stargazers_count":0,
     "watchers_count":0,
     "language":null,
     "has_issues":false,
     "has_projects":true,
     "has_downloads":true,
     "has_wiki":true,
     "has_pages":false,
     "forks_count":0,
     "mirror_url":null,
     "archived":false,
     "disabled":false,
     "open_issues_count":0,
     "license":null,
     "forks":0,
     "open_issues":0,
     "watchers":0,
     "default_branch":"master",
     "permissions":{
        "admin":true,
        "push":true,
        "pull":true
     },
     "parent":{
        "id":271353637,
        "node_id":"MDEwOlJlcG9zaXRvcnkyNzEzNTM2Mzc=",
        "name":"HelloWorld",
        "full_name":"Kristie-Tom-Test/HelloWorld",
        "private":false,
        "owner":[
           "Object"
        ],
        "html_url":"https://github.com/Kristie-Tom-Test/HelloWorld",
        "description":null,
        "fork":false,
        "url":"https://api.github.com/repos/Kristie-Tom-Test/HelloWorld",
        "forks_url":"https://api.github.com/repos/Kristie-Tom-Test/HelloWorld/forks",
        "keys_url":"https://api.github.com/repos/Kristie-Tom-Test/HelloWorld/keys{/key_id}",
        "collaborators_url":"https://api.github.com/repos/Kristie-Tom-Test/HelloWorld/collaborators{/collaborator}",
        "teams_url":"https://api.github.com/repos/Kristie-Tom-Test/HelloWorld/teams",
        "hooks_url":"https://api.github.com/repos/Kristie-Tom-Test/HelloWorld/hooks",
        "issue_events_url":"https://api.github.com/repos/Kristie-Tom-Test/HelloWorld/issues/events{/number}",
        "events_url":"https://api.github.com/repos/Kristie-Tom-Test/HelloWorld/events",
        "assignees_url":"https://api.github.com/repos/Kristie-Tom-Test/HelloWorld/assignees{/user}",
        "branches_url":"https://api.github.com/repos/Kristie-Tom-Test/HelloWorld/branches{/branch}",
        "tags_url":"https://api.github.com/repos/Kristie-Tom-Test/HelloWorld/tags",
        "blobs_url":"https://api.github.com/repos/Kristie-Tom-Test/HelloWorld/git/blobs{/sha}",
        "git_tags_url":"https://api.github.com/repos/Kristie-Tom-Test/HelloWorld/git/tags{/sha}",
        "git_refs_url":"https://api.github.com/repos/Kristie-Tom-Test/HelloWorld/git/refs{/sha}",
        "trees_url":"https://api.github.com/repos/Kristie-Tom-Test/HelloWorld/git/trees{/sha}",
        "statuses_url":"https://api.github.com/repos/Kristie-Tom-Test/HelloWorld/statuses/{sha}",
        "languages_url":"https://api.github.com/repos/Kristie-Tom-Test/HelloWorld/languages",
        "stargazers_url":"https://api.github.com/repos/Kristie-Tom-Test/HelloWorld/stargazers",
        "contributors_url":"https://api.github.com/repos/Kristie-Tom-Test/HelloWorld/contributors",
        "subscribers_url":"https://api.github.com/repos/Kristie-Tom-Test/HelloWorld/subscribers",
        "subscription_url":"https://api.github.com/repos/Kristie-Tom-Test/HelloWorld/subscription",
        "commits_url":"https://api.github.com/repos/Kristie-Tom-Test/HelloWorld/commits{/sha}",
        "git_commits_url":"https://api.github.com/repos/Kristie-Tom-Test/HelloWorld/git/commits{/sha}",
        "comments_url":"https://api.github.com/repos/Kristie-Tom-Test/HelloWorld/comments{/number}",
        "issue_comment_url":"https://api.github.com/repos/Kristie-Tom-Test/HelloWorld/issues/comments{/number}",
        "contents_url":"https://api.github.com/repos/Kristie-Tom-Test/HelloWorld/contents/{+path}",
        "compare_url":"https://api.github.com/repos/Kristie-Tom-Test/HelloWorld/compare/{base}...{head}",
        "merges_url":"https://api.github.com/repos/Kristie-Tom-Test/HelloWorld/merges",
        "archive_url":"https://api.github.com/repos/Kristie-Tom-Test/HelloWorld/{archive_format}{/ref}",
        "downloads_url":"https://api.github.com/repos/Kristie-Tom-Test/HelloWorld/downloads",
        "issues_url":"https://api.github.com/repos/Kristie-Tom-Test/HelloWorld/issues{/number}",
        "pulls_url":"https://api.github.com/repos/Kristie-Tom-Test/HelloWorld/pulls{/number}",
        "milestones_url":"https://api.github.com/repos/Kristie-Tom-Test/HelloWorld/milestones{/number}",
        "notifications_url":"https://api.github.com/repos/Kristie-Tom-Test/HelloWorld/notifications{?since,all,participating}",
        "labels_url":"https://api.github.com/repos/Kristie-Tom-Test/HelloWorld/labels{/name}",
        "releases_url":"https://api.github.com/repos/Kristie-Tom-Test/HelloWorld/releases{/id}",
        "deployments_url":"https://api.github.com/repos/Kristie-Tom-Test/HelloWorld/deployments",
        "created_at":"2020-06-10T18:24:17Z",
        "updated_at":"2020-06-10T18:27:31Z",
        "pushed_at":"2020-06-10T18:27:29Z",
        "git_url":"git://github.com/Kristie-Tom-Test/HelloWorld.git",
        "ssh_url":"git@github.com:Kristie-Tom-Test/HelloWorld.git",
        "clone_url":"https://github.com/Kristie-Tom-Test/HelloWorld.git",
        "svn_url":"https://github.com/Kristie-Tom-Test/HelloWorld",
        "homepage":null,
        "size":0,
        "stargazers_count":0,
        "watchers_count":0,
        "language":null,
        "has_issues":true,
        "has_projects":true,
        "has_downloads":true,
        "has_wiki":true,
        "has_pages":false,
        "forks_count":2,
        "mirror_url":null,
        "archived":false,
        "disabled":false,
        "open_issues_count":0,
        "license":null,
        "forks":2,
        "open_issues":0,
        "watchers":0,
        "default_branch":"master"
     },
     "source":{
        "id":271353637,
        "node_id":"MDEwOlJlcG9zaXRvcnkyNzEzNTM2Mzc=",
        "name":"HelloWorld",
        "full_name":"Kristie-Tom-Test/HelloWorld",
        "private":false,
        "owner":[
           "Object"
        ],
        "html_url":"https://github.com/Kristie-Tom-Test/HelloWorld",
        "description":null,
        "fork":false,
        "url":"https://api.github.com/repos/Kristie-Tom-Test/HelloWorld",
        "forks_url":"https://api.github.com/repos/Kristie-Tom-Test/HelloWorld/forks",
        "keys_url":"https://api.github.com/repos/Kristie-Tom-Test/HelloWorld/keys{/key_id}",
        "collaborators_url":"https://api.github.com/repos/Kristie-Tom-Test/HelloWorld/collaborators{/collaborator}",
        "teams_url":"https://api.github.com/repos/Kristie-Tom-Test/HelloWorld/teams",
        "hooks_url":"https://api.github.com/repos/Kristie-Tom-Test/HelloWorld/hooks",
        "issue_events_url":"https://api.github.com/repos/Kristie-Tom-Test/HelloWorld/issues/events{/number}",
        "events_url":"https://api.github.com/repos/Kristie-Tom-Test/HelloWorld/events",
        "assignees_url":"https://api.github.com/repos/Kristie-Tom-Test/HelloWorld/assignees{/user}",
        "branches_url":"https://api.github.com/repos/Kristie-Tom-Test/HelloWorld/branches{/branch}",
        "tags_url":"https://api.github.com/repos/Kristie-Tom-Test/HelloWorld/tags",
        "blobs_url":"https://api.github.com/repos/Kristie-Tom-Test/HelloWorld/git/blobs{/sha}",
        "git_tags_url":"https://api.github.com/repos/Kristie-Tom-Test/HelloWorld/git/tags{/sha}",
        "git_refs_url":"https://api.github.com/repos/Kristie-Tom-Test/HelloWorld/git/refs{/sha}",
        "trees_url":"https://api.github.com/repos/Kristie-Tom-Test/HelloWorld/git/trees{/sha}",
        "statuses_url":"https://api.github.com/repos/Kristie-Tom-Test/HelloWorld/statuses/{sha}",
        "languages_url":"https://api.github.com/repos/Kristie-Tom-Test/HelloWorld/languages",
        "stargazers_url":"https://api.github.com/repos/Kristie-Tom-Test/HelloWorld/stargazers",
        "contributors_url":"https://api.github.com/repos/Kristie-Tom-Test/HelloWorld/contributors",
        "subscribers_url":"https://api.github.com/repos/Kristie-Tom-Test/HelloWorld/subscribers",
        "subscription_url":"https://api.github.com/repos/Kristie-Tom-Test/HelloWorld/subscription",
        "commits_url":"https://api.github.com/repos/Kristie-Tom-Test/HelloWorld/commits{/sha}",
        "git_commits_url":"https://api.github.com/repos/Kristie-Tom-Test/HelloWorld/git/commits{/sha}",
        "comments_url":"https://api.github.com/repos/Kristie-Tom-Test/HelloWorld/comments{/number}",
        "issue_comment_url":"https://api.github.com/repos/Kristie-Tom-Test/HelloWorld/issues/comments{/number}",
        "contents_url":"https://api.github.com/repos/Kristie-Tom-Test/HelloWorld/contents/{+path}",
        "compare_url":"https://api.github.com/repos/Kristie-Tom-Test/HelloWorld/compare/{base}...{head}",
        "merges_url":"https://api.github.com/repos/Kristie-Tom-Test/HelloWorld/merges",
        "archive_url":"https://api.github.com/repos/Kristie-Tom-Test/HelloWorld/{archive_format}{/ref}",
        "downloads_url":"https://api.github.com/repos/Kristie-Tom-Test/HelloWorld/downloads",
        "issues_url":"https://api.github.com/repos/Kristie-Tom-Test/HelloWorld/issues{/number}",
        "pulls_url":"https://api.github.com/repos/Kristie-Tom-Test/HelloWorld/pulls{/number}",
        "milestones_url":"https://api.github.com/repos/Kristie-Tom-Test/HelloWorld/milestones{/number}",
        "notifications_url":"https://api.github.com/repos/Kristie-Tom-Test/HelloWorld/notifications{?since,all,participating}",
        "labels_url":"https://api.github.com/repos/Kristie-Tom-Test/HelloWorld/labels{/name}",
        "releases_url":"https://api.github.com/repos/Kristie-Tom-Test/HelloWorld/releases{/id}",
        "deployments_url":"https://api.github.com/repos/Kristie-Tom-Test/HelloWorld/deployments",
        "created_at":"2020-06-10T18:24:17Z",
        "updated_at":"2020-06-10T18:27:31Z",
        "pushed_at":"2020-06-10T18:27:29Z",
        "git_url":"git://github.com/Kristie-Tom-Test/HelloWorld.git",
        "ssh_url":"git@github.com:Kristie-Tom-Test/HelloWorld.git",
        "clone_url":"https://github.com/Kristie-Tom-Test/HelloWorld.git",
        "svn_url":"https://github.com/Kristie-Tom-Test/HelloWorld",
        "homepage":null,
        "size":0,
        "stargazers_count":0,
        "watchers_count":0,
        "language":null,
        "has_issues":true,
        "has_projects":true,
        "has_downloads":true,
        "has_wiki":true,
        "has_pages":false,
        "forks_count":2,
        "mirror_url":null,
        "archived":false,
        "disabled":false,
        "open_issues_count":0,
        "license":null,
        "forks":2,
        "open_issues":0,
        "watchers":0,
        "default_branch":"master"
     },
     "network_count":2,
     "subscribers_count":0
  }
}